moti/__init__.py
moti/cli.py
moti-0.1.9.dist-info/licenses/LICENSE
moti-0.1.9.dist-info/METADATA
moti-0.1.9.dist-info/WHEEL
moti-0.1.9.dist-info/entry_points.txt
moti-0.1.9.dist-info/top_level.txt
moti-0.1.9.dist-info/RECORD
